enumx/__init__.py
enumx/enumx.py
enumx-0.0.2.dist-info/LICENSE
enumx-0.0.2.dist-info/METADATA
enumx-0.0.2.dist-info/WHEEL
enumx-0.0.2.dist-info/top_level.txt
enumx-0.0.2.dist-info/RECORD
