Metadata-Version: 2.1
Name: enumx
Version: 0.0.2
Summary: An extended enum for python.
Home-page: https://github.com/RichardLiew/enumx.git
Author: Richard
Author-email: richard.zen.liew@gmail.com
Classifier: Programming Language :: Python :: 3
Classifier: License :: OSI Approved :: MIT License
Classifier: Operating System :: OS Independent
Requires-Python: >=3.7
License-File: LICENSE
